{
    "User_ID": 100,
    "Comments": "All data string are variable, DMS quantity and type of messages will change daily for each patient. Messages with Return Responses can nest. Message Content will have variable fields filled in by CPM and can vary between each patient. Message quantities will vary from day to day.",
    "Data": {
        "Version": "2.1",
        "EventDateTime": "2015-04-21T15:22:00.472Z"
    },
    "CP_Feed": [
        {
          
            "Feed": {
             
                "FeedDate":"2015-07-01",

                "DMS": [
                    {
                        "MessageID": "CF_SOL_HELO_01",
                        "Obs_Key": "Other",
                        "ParentID": "601",
                        "MessageIcon": "info",
                        "MessageContent": "Good Morning! CarePlan Manager recommends that you take your medications, eat healthy and exercise.",
                        "ReturnFieldType": "None",
                        "ReturnDataRangeLow": null,
                        "ReturnDataRangeHigh": null,
                        "ReturnValidAnswers": null,
                        "PatientAnswer": null,
                        "ResponseDate": null
                    },
                    {
                        "MessageID": "CF_REM_NAG_01",
                        "Obs_Key": "Other",
                        "ParentID": "601",
                        "MessageIcon": "info",
                        "MessageContent": "We have not received your fasting blood sugar today. Please type RPT to send ASAP.",
                        "ReturnFieldType": "None",
                        "ReturnDataRangeLow": null,
                        "ReturnDataRangeHigh": null,
                        "ReturnValidAnswers": null,
                        "PatientAnswer": null,
                        "ResponseDate": null
                    },
                    {
                        "MessageID": "CF_SOL_MED_BP",
                        "Obs_Key": "Adherence",
                        "ParentID": "601",
                        "MessageIcon": "question",
                        "MessageContent": "Did you take all your BP meds as instructed today? (Y or N)",
                        "ReturnFieldType": "List",
                        "ReturnDataRangeLow": null,
                        "ReturnDataRangeHigh": null,
                        "ReturnValidAnswers": "Y,N",
                        "PatientAnswer": "Y",
                        "ResponseDate": "2015-07-01 17:34:56"
                    },
                    {
                        "MessageID": "CF_SOL_MED_OD",
                        "Obs_Key": "Adherence",
                        "ParentID": "601",
                        "MessageIcon": "question",
                        "MessageContent": "Did you take all your oral diabetes meds as instructed today? (Y or N)",
                        "ReturnFieldType": "List",
                        "ReturnDataRangeLow": null,
                        "ReturnDataRangeHigh": null,
                        "ReturnValidAnswers": "Y,N",
                        "PatientAnswer": null,
                        "ResponseDate": null
                    },
                    {
                        "MessageID": "CF_TOD_AFB_01",
                        "Obs_Key": "TOD",
                        "ParentID": "601",
                        "MessageIcon": "tip",
                        "MessageContent": "You can eat dessert! Try fruit, low-fat or nonfat versions of treats such as ice cream, or cakes and cookies made with unsaturated fats.",
                        "ReturnFieldType": "None",
                        "ReturnDataRangeLow": null,
                        "ReturnDataRangeHigh": null,
                        "ReturnValidAnswers": null,
                        "PatientAnswer": null,
                        "ResponseDate": null
                    }
                ],
                "Reminders": [
                    {
                        "MessageID": "CF_DM_10",
                        "Obs_Key": "Other",
                        "ParentID": "604",
                        "MessageIcon": "reminder",
                        "MessageContent": "Good Morning! CarePlan Manager recommends that you take your medications, eat healthy and exercise. Please remember to send us your number of cigarettes smoked, weight, fasting blood sugar, resting blood pressure by texting RPT today.",
                        "ReturnFieldType": "None",
                        "ReturnDataRangeLow": null,
                        "ReturnDataRangeHigh": null,
                        "ReturnValidAnswers": null,
                        "PatientAnswer": null,
                        "ResponseDate": null
                    },
                    {
                        "MessageID": "CF_DM_HSP_10",
                        "Obs_Key": "HSP_DM",
                        "ParentID": "604",
                        "MessageIcon": "hsp",
                        "MessageContent": "If you are in the hospital now or have recently been discharged from the hospital or emergency room. 1. Visited the Emergency Room 2: Admitted to the Hospital",
                        "ReturnFieldType": "List",
                        "ReturnDataRangeLow": null,
                        "ReturnDataRangeHigh": null,
                        "ReturnValidAnswers": "1,2",
                        "PatientAnswer": "1",
                        "ResponseDate": "2015-07-01 10:01:25",
                        "Response": {
                            "MessageID": "CF_HSP_20",
                            "Obs_Key": "HSP_ER",
                            "ParentID": "604",
                            "MessageIcon": "question",
                            "MessageContent": "Sorry to hear! Please type the date you were discharged (in mm/dd format) or one letter from below list: C. Currently in the hospital",
                            "ReturnFieldType": "OPEN",
                            "ReturnDataRangeLow": null,
                            "ReturnDataRangeHigh": null,
                            "ReturnValidAnswers": null,
                            "PatientAnswer": "C",
                            "ResponseDate": "2015-07-01 10:01:49",
                            "Response": {
                                "MessageID": "CF_HSP_EX_10",
                                "Obs_Key": "Other",
                                "ParentID": "603",
                                "MessageIcon": "question",
                                "MessageContent": "Thank you. Your provider is being informed.",
                                "ReturnFieldType": "None",
                                "ReturnDataRangeLow": null,
                                "ReturnDataRangeHigh": null,
                                "ReturnValidAnswers": null,
                                "PatientAnswer": null,
                                "ResponseDate": null
                            }
                        }
                    }
                ],
                "Biometric": [
                    {
                        "MessageID": "CF_RPT_20",
                        "Obs_Key": "Blood_Pressure",
                        "ParentID": "602",
                        "MessageIcon": "bp",
                        "MessageContent": "Enter a resting BP level taken today (Example: 125/75)",
                        "ReturnFieldType": "Range",
                        "ReturnDataRangeLow": "101/50",
                        "ReturnDataRangeHigh": "250/130",
                        "ReturnValidAnswers": null,
                        "PatientAnswer": "125/86",
                        "ResponseDate": "2015-07-01 09:48:42",
                        "Response": {
                            "MessageID": "CF_RPT_BP_10",
                            "Obs_Key": "Other",
                            "ParentID": "601",
                            "MessageIcon": "info",
                            "MessageContent": "Congratulations!  Your BP is where it should be.  Keep up the good work and remember to check your resting BP at the same time each day.",
                            "ReturnFieldType": "None",
                            "ReturnDataRangeLow": null,
                            "ReturnDataRangeHigh": null,
                            "ReturnValidAnswers": null,
                            "PatientAnswer": null,
                            "ResponseDate": null
                        }
                    },
                    {
                        "MessageID": "CF_RPT_30",
                        "Obs_Key": "Blood_Sugar",
                        "ParentID": "602",
                        "MessageIcon": "bs",
                        "MessageContent": "Enter today's fasting BS level (Example: 125)",
                        "ReturnFieldType": "Range",
                        "ReturnDataRangeLow": "31",
                        "ReturnDataRangeHigh": "550",
                        "ReturnValidAnswers": null,
                        "PatientAnswer": "328",
                        "ResponseDate": "2015-07-01 09:35:24",
                        "Response": {
                            "MessageID": "CF_RPT_BS_60",
                            "Obs_Key": "Other",
                            "ParentID": "602",
                            "MessageIcon": "info",
                            "MessageContent": "Your BS reading is extremely high. If this is an emergency, call 911 or your clinic, or go to the ER. Take your meds, eat healthy foods, and retest regularly. We've notified your clinic.",
                            "ReturnFieldType": "None",
                            "ReturnDataRangeLow": null,
                            "ReturnDataRangeHigh": null,
                            "ReturnValidAnswers": null,
                            "PatientAnswer": null,
                            "ResponseDate": null
                        }
                    },
                    {
                        "MessageID": "CF_RPT_40",
                        "Obs_Key": "Weight",
                        "ParentID": "602",
                        "MessageIcon": "wt",
                        "MessageContent": "Enter your weight in pounds (lbs) (Example: 175)",
                        "ReturnFieldType": "Range",
                        "ReturnDataRangeLow": "50",
                        "ReturnDataRangeHigh": "500",
                        "ReturnValidAnswers": null,
                        "PatientAnswer": null,
                        "ResponseDate": null
                    },
                    {
                        "MessageID": "CF_RPT_50",
                        "Obs_Key": "Cigarettes",
                        "ParentID": "602",
                        "MessageIcon": "cs",
                        "MessageContent": "Enter the number of cigarettes smoked in the last 24 hours.",
                        "ReturnFieldType": "Range",
                        "ReturnDataRangeLow": "0",
                        "ReturnDataRangeHigh": "120",
                        "ReturnValidAnswers": null,
                        "PatientAnswer": null,
                        "ResponseDate": null
                    },
                    {
                        "MessageID": "CF_SYM_70",
                        "Obs_Key": "Call",
                        "ParentID": "602",
                        "MessageIcon": "call",
                        "MessageContent": "Request a call from the Clinic.",
                        "ReturnFieldType": "List",
                        "ReturnDataRangeLow": null,
                        "ReturnDataRangeHigh": null,
                        "ReturnValidAnswers": "Y",
                        "PatientAnswer": "Y",
                        "ResponseDate": "2015-07-01 01:12:54",
                        "Response": {
                            "MessageID": "CF_SYM_40",
                            "Obs_Key": "Other",
                            "ParentID": "602",
                            "MessageIcon": "emergency",
                            "MessageContent": "If this is a medical emergency, call 911 or go to an emergency center. Your clinic is being notified.",
                            "ReturnFieldType": "None",
                            "ReturnDataRangeLow": null,
                            "ReturnDataRangeHigh": null,
                            "ReturnValidAnswers": null,
                            "PatientAnswer": null,
                            "ResponseDate": null
                        }
                    }
                ],
                "Symptoms": [
                    {
                        "MessageID": "CF_SYM_11",
                        "Obs_Key": "Severity",
                        "ParentID": "603",
                        "MessageIcon": "question",
                        "MessageContent": "Shortness of breath",
                        "ReturnFieldType": "Range",
                        "ReturnDataRangeLow": "0",
                        "ReturnDataRangeHigh": "9",
                        "ReturnValidAnswers": null,
                        "PatientAnswer": 5,
                        "ResponseDate": "2015-07-01 11:42:14",
                        "Response": {
                            "MessageID": "CF_SYM_40",
                            "Obs_Key": "Other",
                            "ParentID": "603",
                            "MessageIcon": "info",
                            "MessageContent": "We are sorry that you are having Problems. Call the clinic if it continues, or gets worse (over 6 on scale of 0-9)",
                            "ReturnFieldType": "None",
                            "ReturnDataRangeLow": null,
                            "ReturnDataRangeHigh": null,
                            "ReturnValidAnswers": null,
                            "PatientAnswer": null,
                            "ResponseDate": null
                        }
                    },
                    {
                        "MessageID": "CF_SYM_12",
                        "Obs_Key": "Symptom",
                        "ParentID": "603",
                        "MessageIcon": "question",
                        "MessageContent": "Coughing or wheezing",
                        "ReturnFieldType": "Range",
                        "ReturnDataRangeLow": "0",
                        "ReturnDataRangeHigh": "9",
                        "ReturnValidAnswers": null,
                        "PatientAnswer": 8,
                        "ResponseDate": "2015-07-01 13:14:42",
                        "Response": {
                            "MessageID": "CF_SYM_70",
                            "Obs_Key": "Severity",
                            "ParentID": "603",
                            "MessageIcon": "emergency",
                            "MessageContent": "If this is a medical emergency, please call 911 or go to an Emergency Center. Someone from the clinic will call you within the next day.",
                            "ReturnFieldType": "None",
                            "ReturnDataRangeLow": null,
                            "ReturnDataRangeHigh": null,
                            "ReturnValidAnswers": null,
                            "PatientAnswer": null,
                            "ResponseDate": null
                        }
                    },
                    {
                        "MessageID": "CF_SYM_13",
                        "Obs_Key": "Symptom",
                        "ParentID": "603",
                        "MessageIcon": "question",
                        "MessageContent": "Chest pain or Chest tightness",
                        "ReturnFieldType": "Range",
                        "ReturnDataRangeLow": "0",
                        "ReturnDataRangeHigh": "9",
                        "ReturnValidAnswers": null,
                        "PatientAnswer": null,
                        "ResponseDate": null
                    },
                    {
                        "MessageID": "CF_SYM_14",
                        "Obs_Key": "Symptom",
                        "ParentID": "603",
                        "MessageIcon": "question",
                        "MessageContent": "Fatigue",
                        "ReturnFieldType": "Range",
                        "ReturnDataRangeLow": "0",
                        "ReturnDataRangeHigh": "9",
                        "ReturnValidAnswers": null,
                        "PatientAnswer": null,
                        "ResponseDate": null
                    },
                    {
                        "MessageID": "CF_SYM_15",
                        "Obs_Key": "Symptom",
                        "ParentID": "603",
                        "MessageIcon": "question",
                        "MessageContent": "Weakness or dizziness",
                        "ReturnFieldType": "Range",
                        "ReturnDataRangeLow": "0",
                        "ReturnDataRangeHigh": "9",
                        "ReturnValidAnswers": null,
                        "PatientAnswer": null,
                        "ResponseDate": null
                    },
                    {
                        "MessageID": "CF_SYM_16",
                        "Obs_Key": "Symptom",
                        "ParentID": "603",
                        "MessageIcon": "question",
                        "MessageContent": "Swelling in legs/feet",
                        "ReturnFieldType": "Range",
                        "ReturnDataRangeLow": "0",
                        "ReturnDataRangeHigh": "9",
                        "ReturnValidAnswers": null,
                        "PatientAnswer": null,
                        "ResponseDate": null
                    },
                    {
                        "MessageID": "CF_SYM_17",
                        "Obs_Key": "Symptom",
                        "ParentID": "603",
                        "MessageIcon": "question",
                        "MessageContent": "Feeling down, a sense of helplessness or sleep changes/problems",
                        "ReturnFieldType": "Range",
                        "ReturnDataRangeLow": "0",
                        "ReturnDataRangeHigh": "9",
                        "ReturnValidAnswers": null,
                        "PatientAnswer": null,
                        "ResponseDate": null
                    },
                    {
                        "MessageID": "CF_SYM_70",
                        "Obs_Key": "Call",
                        "ParentID": "603",
                        "MessageIcon": "question",
                        "MessageContent": "Please have clinic call me",
                        "ReturnFieldType": "Range",
                        "ReturnDataRangeLow": "0",
                        "ReturnDataRangeHigh": "9",
                        "ReturnValidAnswers": null,
                        "PatientAnswer": null,
                        "ResponseDate": null
                    }
                ]
          }
        },
        {
          
     "Feed": {
           
          "FeedDate":"2015-06-30",
 
                "DMS": [
                    {
                        "MessageID": "CF_SOL_HELO_01",
                        "Obs_Key": "Other",
                        "ParentID": "601",
                        "MessageIcon": "info",
                        "MessageContent": "Good Morning! CarePlan Manager recommends that you take your medications, eat healthy and exercise.",
                        "ReturnFieldType": "None",
                        "ReturnDataRangeLow": null,
                        "ReturnDataRangeHigh": null,
                        "ReturnValidAnswers": null,
                        "PatientAnswer": null,
                        "ResponseDate": null
                    },
                    {
                        "MessageID": "CF_REM_NAG_01",
                        "Obs_Key": "Other",
                        "ParentID": "601",
                        "MessageIcon": "info",
                        "MessageContent": "We have not received your fasting blood pressure today. Please type RPT to send ASAP.",
                        "ReturnFieldType": "None",
                        "ReturnDataRangeLow": null,
                        "ReturnDataRangeHigh": null,
                        "ReturnValidAnswers": null,
                        "PatientAnswer": null,
                        "ResponseDate": null
                    },
                    {
                        "MessageID": "CF_SOL_MED_OT",
                        "Obs_Key": "Adherence",
                        "ParentID": "601",
                        "MessageIcon": "question",
                        "MessageContent": "Did you take all your other meds as instructed today? (Y or N)",
                        "ReturnFieldType": "List",
                        "ReturnDataRangeLow": null,
                        "ReturnDataRangeHigh": null,
                        "ReturnValidAnswers": "Y,N",
                        "PatientAnswer": "Y",
                        "ResponseDate": "2015-06-30 12:46:85"
                    },
                    {
                        "MessageID": "CF_SOL_MED_CO",
                        "Obs_Key": "Adherence",
                        "ParentID": "601",
                        "MessageIcon": "question",
                        "MessageContent": "Did you take all your COPD meds as instructed today? (Y or N)",
                        "ReturnFieldType": "List",
                        "ReturnDataRangeLow": null,
                        "ReturnDataRangeHigh": null,
                        "ReturnValidAnswers": "Y,N",
                        "PatientAnswer": "Y",
                        "ResponseDate": "2015-06-30 18:42:26"
                    },
                    {
                        "MessageID": "CF_TOD_AFB_01",
                        "Obs_Key": "TOD",
                        "ParentID": "601",
                        "MessageIcon": "tip",
                        "MessageContent": "You can eat dessert! Try fruit, low-fat or nonfat versions of treats such as ice cream, or cakes and cookies made with unsaturated fats.",
                        "ReturnFieldType": "None",
                        "ReturnDataRangeLow": null,
                        "ReturnDataRangeHigh": null,
                        "ReturnValidAnswers": null,
                        "PatientAnswer": null,
                        "ResponseDate": null
                    }
                ],
                "Reminders": [
                    {
                        "MessageID": "CF_DM_10",
                        "Obs_Key": "Other",
                        "ParentID": "604",
                        "MessageIcon": "reminder",
                        "MessageContent": "Good Morning! CarePlan Manager recommends that you take your medications, eat healthy and exercise. Please remember to send us your number of cigarettes smoked, weight, fasting blood sugar, resting blood pressure by texting RPT today.",
                        "ReturnFieldType": "None",
                        "ReturnDataRangeLow": null,
                        "ReturnDataRangeHigh": null,
                        "ReturnValidAnswers": null,
                        "PatientAnswer": null,
                        "ResponseDate": null
                    },
                    {
                        "MessageID": "CF_DM_HSP_10",
                        "Obs_Key": "HSP_DM",
                        "ParentID": "604",
                        "MessageIcon": "hsp",
                        "MessageContent": "If you are in the hospital now or have recently been discharged from the hospital or emergency room. 1. Visited the Emergency Room 2: Admitted to the Hospital",
                        "ReturnFieldType": "List",
                        "ReturnDataRangeLow": null,
                        "ReturnDataRangeHigh": null,
                        "ReturnValidAnswers": "1,2",
                        "PatientAnswer": null,
                        "ResponseDate": null
                    }
                ],
                "Biometric": [
                    {
                        "MessageID": "CF_RPT_20",
                        "Obs_Key": "Blood_Pressure",
                        "ParentID": "602",
                        "MessageIcon": "bp",
                        "MessageContent": "Enter a resting BP level taken today (Example: 125/75)",
                        "ReturnFieldType": "Range",
                        "ReturnDataRangeLow": "101/50",
                        "ReturnDataRangeHigh": "250/130",
                        "ReturnValidAnswers": null,
                        "PatientAnswer": "115/81",
                        "ResponseDate": "2015-06-30 11:18:45",
                        "Response": {
                            "MessageID": "CF_RPT_BP_10",
                            "Obs_Key": "Other",
                            "ParentID": "601",
                            "MessageIcon": "info",
                            "MessageContent": "Congratulations!  Your BP is where it should be.  Keep up the good work and remember to check your resting BP at the same time each day.",
                            "ReturnFieldType": "None",
                            "ReturnDataRangeLow": null,
                            "ReturnDataRangeHigh": null,
                            "ReturnValidAnswers": null,
                            "PatientAnswer": null,
                            "ResponseDate": null
                        }
                    },
                    {
                        "MessageID": "CF_RPT_30",
                        "Obs_Key": "Blood_Sugar",
                        "ParentID": "602",
                        "MessageIcon": "bs",
                        "MessageContent": "Enter today's fasting BS level (Example: 125)",
                        "ReturnFieldType": "Range",
                        "ReturnDataRangeLow": "31",
                        "ReturnDataRangeHigh": "550",
                        "ReturnValidAnswers": null,
                        "PatientAnswer": "326",
                        "ResponseDate": "2015-06-30 18:27:25",
                        "Response": {
                            "MessageID": "CF_RPT_BS_60",
                            "Obs_Key": "Other",
                            "ParentID": "602",
                            "MessageIcon": "info",
                            "MessageContent": "Your BS reading is extremely high. If this is an emergency, call 911 or your clinic, or go to the ER. Take your meds, eat healthy foods, and retest regularly. We've notified your clinic.",
                            "ReturnFieldType": "None",
                            "ReturnDataRangeLow": null,
                            "ReturnDataRangeHigh": null,
                            "ReturnValidAnswers": null,
                            "PatientAnswer": null,
                            "ResponseDate": null
                        }
                    },
                    {
                        "MessageID": "CF_RPT_40",
                        "Obs_Key": "Weight",
                        "ParentID": "602",
                        "MessageIcon": "wt",
                        "MessageContent": "Enter your weight in pounds (lbs) (Example: 175)",
                        "ReturnFieldType": "Range",
                        "ReturnDataRangeLow": "50",
                        "ReturnDataRangeHigh": "500",
                        "ReturnValidAnswers": null,
                        "PatientAnswer": "288",
                        "ResponseDate": "2015-06-30 16:45:28",
                        "Response": {
                            "MessageID": "CF_RPT_WT_70",
                            "Obs_Key": "Other",
                            "ParentID": "602",
                            "MessageIcon": "info",
                            "MessageContent": "Your Weight reading is getting higher. Take your meds, eat healthy foods, and retest regularly. We've notified your clinic.",
                            "ReturnFieldType": "None",
                            "ReturnDataRangeLow": null,
                            "ReturnDataRangeHigh": null,
                            "ReturnValidAnswers": null,
                            "PatientAnswer": null,
                            "ResponseDate": null
                        }
                    },
                    {
                        "MessageID": "CF_RPT_50",
                        "Obs_Key": "Cigarettes",
                        "ParentID": "602",
                        "MessageIcon": "cs",
                        "MessageContent": "Enter the number of cigarettes smoked in the last 24 hours.",
                        "ReturnFieldType": "Range",
                        "ReturnDataRangeLow": "0",
                        "ReturnDataRangeHigh": "120",
                        "ReturnValidAnswers": null,
                        "PatientAnswer": null,
                        "ResponseDate": null
                    },
                    {
                        "MessageID": "CF_SYM_70",
                        "Obs_Key": "Call",
                        "ParentID": "602",
                        "MessageIcon": "call",
                        "MessageContent": "Request a call from the Clinic.",
                        "ReturnFieldType": "List",
                        "ReturnDataRangeLow": null,
                        "ReturnDataRangeHigh": null,
                        "ReturnValidAnswers": "Y",
                        "PatientAnswer": null,
                        "ResponseDate": null
                    }
                ],
                "Symptoms": []
            }
       },
        {
       

 "Feed": {
           
                "FeedDate":"2015-06-29",

               "DMS": [
                    {
                        "MessageID": "CF_SOL_HELO_01",
                        "Obs_Key": "Other",
                        "ParentID": "601",
                        "MessageIcon": "info",
                        "MessageContent": "Good Morning! CarePlan Manager recommends that you take your medications, eat healthy and exercise.",
                        "ReturnFieldType": "None",
                        "ReturnDataRangeLow": null,
                        "ReturnDataRangeHigh": null,
                        "ReturnValidAnswers": null,
                        "PatientAnswer": null,
                        "ResponseDate": null
                    },
                    {
                        "MessageID": "CF_REM_NAG_01",
                        "Obs_Key": "Other",
                        "ParentID": "601",
                        "MessageIcon": "info",
                        "MessageContent": "We have not received your weight reading today. Please type RPT to send ASAP.",
                        "ReturnFieldType": "None",
                        "ReturnDataRangeLow": null,
                        "ReturnDataRangeHigh": null,
                        "ReturnValidAnswers": null,
                        "PatientAnswer": null,
                        "ResponseDate": null
                    },
                    {
                        "MessageID": "CF_SOL_MED_WP",
                        "Obs_Key": "Adherence",
                        "ParentID": "601",
                        "MessageIcon": "question",
                        "MessageContent": "Did you take all your Water Pills as instructed today? (Y or N)",
                        "ReturnFieldType": "List",
                        "ReturnDataRangeLow": null,
                        "ReturnDataRangeHigh": null,
                        "ReturnValidAnswers": "Y,N",
                        "PatientAnswer": "N",
                        "ResponseDate": null
                    },
                    {
                        "MessageID": "CF_SOL_MED_OD",
                        "Obs_Key": "Adherence",
                        "ParentID": "601",
                        "MessageIcon": "question",
                        "MessageContent": "Did you take all your depression meds as instructed today? (Y or N)",
                        "ReturnFieldType": "List",
                        "ReturnDataRangeLow": null,
                        "ReturnDataRangeHigh": null,
                        "ReturnValidAnswers": "Y,N",
                        "PatientAnswer": "N",
                        "ResponseDate": "2015-06-29 18:53:12"
                    },
                    {
                        "MessageID": "CF_SOL_MED_ALG_01",
                        "Obs_Key": "ALG",
                        "ParentID": "601",
                        "MessageIcon": "info",
                        "MessageContent": "Missing medications more than 3 times per week lowers thier effectiveness.",
                        "ReturnFieldType": "None",
                        "ReturnDataRangeLow": null,
                        "ReturnDataRangeHigh": null,
                        "ReturnValidAnswers": null,
                        "PatientAnswer": null,
                        "ResponseDate": null
                    },
                    {
                        "MessageID": "CF_TOD_AFB_01",
                        "Obs_Key": "TOD",
                        "ParentID": "601",
                        "MessageIcon": "tip",
                        "MessageContent": "You can eat dessert! Try fruit, low-fat or nonfat versions of treats such as ice cream, or cakes and cookies made with unsaturated fats.",
                        "ReturnFieldType": "None",
                        "ReturnDataRangeLow": null,
                        "ReturnDataRangeHigh": null,
                        "ReturnValidAnswers": null,
                        "PatientAnswer": null,
                        "ResponseDate": null
                    }
                ],
                "Reminders": [
                    {
                        "MessageID": "CF_DM_10",
                        "Obs_Key": "Other",
                        "ParentID": "604",
                        "MessageIcon": "reminder",
                        "MessageContent": "Good Morning! CarePlan Manager recommends that you take your medications, eat healthy and exercise. Please remember to send us your number of cigarettes smoked, weight, fasting blood sugar, resting blood pressure by texting RPT today.",
                        "ReturnFieldType": "None",
                        "ReturnDataRangeLow": null,
                        "ReturnDataRangeHigh": null,
                        "ReturnValidAnswers": null,
                        "PatientAnswer": null,
                        "ResponseDate": null
                    },
                    {
                        "MessageID": "CF_DM_HSP_10",
                        "Obs_Key": "HSP_DM",
                        "ParentID": "604",
                        "MessageIcon": "hsp",
                        "MessageContent": "If you are in the hospital now or have recently been discharged from the hospital or emergency room. 1. Visited the Emergency Room 2: Admitted to the Hospital",
                        "ReturnFieldType": "List",
                        "ReturnDataRangeLow": null,
                        "ReturnDataRangeHigh": null,
                        "ReturnValidAnswers": "1,2",
                        "PatientAnswer": null,
                        "ResponseDate": null
                    }
                ],
                "Biometric": [
                    {
                        "MessageID": "CF_RPT_20",
                        "Obs_Key": "Blood_Pressure",
                        "ParentID": "602",
                        "MessageIcon": "bp",
                        "MessageContent": "Enter a resting BP level taken today (Example: 125/75)",
                        "ReturnFieldType": "Range",
                        "ReturnDataRangeLow": "101/50",
                        "ReturnDataRangeHigh": "250/130",
                        "ReturnValidAnswers": null,
                        "PatientAnswer": "135/88",
                        "ResponseDate": "2015-06-29 12:42:36",
                        "Response": {
                            "MessageID": "CF_RPT_BP_10",
                            "Obs_Key": "Other",
                            "ParentID": "601",
                            "MessageIcon": "info",
                            "MessageContent": "Congratulations!  Your BP is where it should be.  Keep up the good work and remember to check your resting BP at the same time each day.",
                            "ReturnFieldType": "None",
                            "ReturnDataRangeLow": null,
                            "ReturnDataRangeHigh": null,
                            "ReturnValidAnswers": null,
                            "PatientAnswer": null,
                            "ResponseDate": null
                        }
                    },
                    {
                        "MessageID": "CF_RPT_30",
                        "Obs_Key": "Blood_Sugar",
                        "ParentID": "602",
                        "MessageIcon": "bs",
                        "MessageContent": "Enter today's fasting BS level (Example: 125)",
                        "ReturnFieldType": "Range",
                        "ReturnDataRangeLow": "31",
                        "ReturnDataRangeHigh": "550",
                        "ReturnValidAnswers": null,
                        "PatientAnswer": "322",
                        "ResponseDate": "2015-06-29 07:25:26",
                        "Response": {
                            "MessageID": "CF_RPT_BS_60",
                            "Obs_Key": "Other",
                            "ParentID": "602",
                            "MessageIcon": "info",
                            "MessageContent": "Your BS reading is extremely high. If this is an emergency, call 911 or your clinic, or go to the ER. Take your meds, eat healthy foods, and retest regularly. We've notified your clinic.",
                            "ReturnFieldType": "None",
                            "ReturnDataRangeLow": null,
                            "ReturnDataRangeHigh": null,
                            "ReturnValidAnswers": null,
                            "PatientAnswer": null,
                            "ResponseDate": null
                        }
                    },
                    {
                        "MessageID": "CF_RPT_40",
                        "Obs_Key": "Weight",
                        "ParentID": "602",
                        "MessageIcon": "wt",
                        "MessageContent": "Enter your weight in pounds (lbs) (Example: 175)",
                        "ReturnFieldType": "Range",
                        "ReturnDataRangeLow": "50",
                        "ReturnDataRangeHigh": "500",
                        "ReturnValidAnswers": null,
                        "PatientAnswer": null,
                        "ResponseDate": null
                    },
                    {
                        "MessageID": "CF_RPT_50",
                        "Obs_Key": "Cigarettes",
                        "ParentID": "602",
                        "MessageIcon": "cs",
                        "MessageContent": "Enter the number of cigarettes smoked in the last 24 hours.",
                        "ReturnFieldType": "Range",
                        "ReturnDataRangeLow": "0",
                        "ReturnDataRangeHigh": "120",
                        "ReturnValidAnswers": null,
                        "PatientAnswer": null,
                        "ResponseDate": null
                    },
                    {
                        "MessageID": "CF_SYM_70",
                        "Obs_Key": "Call",
                        "ParentID": "602",
                        "MessageIcon": "call",
                        "MessageContent": "Request a call from the Clinic.",
                        "ReturnFieldType": "List",
                        "ReturnDataRangeLow": null,
                        "ReturnDataRangeHigh": null,
                        "ReturnValidAnswers": "Y",
                        "PatientAnswer": null,
                        "ResponseDate": null
                    }
                ],
                "Symptoms": [
                    {
                        "MessageID": "CF_SYM_11",
                        "Obs_Key": "Severity",
                        "ParentID": "603",
                        "MessageIcon": "question",
                        "MessageContent": "Shortness of breath",
                        "ReturnFieldType": "Range",
                        "ReturnDataRangeLow": "0",
                        "ReturnDataRangeHigh": "9",
                        "ReturnValidAnswers": null,
                        "PatientAnswer": 2,
                        "ResponseDate": "2015-06-29 23:41:15",
                        "Response": {
                            "MessageID": "CF_SYM_40",
                            "Obs_Key": "Other",
                            "ParentID": "603",
                            "MessageIcon": "info",
                            "MessageContent": "We are sorry that you are having Problems. Call the clinic if it continues, or gets worse (over 6 on scale of 0-9)",
                            "ReturnFieldType": "None",
                            "ReturnDataRangeLow": null,
                            "ReturnDataRangeHigh": null,
                            "ReturnValidAnswers": null,
                            "PatientAnswer": null,
                            "ResponseDate": null
                        }
                    },
                    {
                        "MessageID": "CF_SYM_12",
                        "Obs_Key": "Symptom",
                        "ParentID": "603",
                        "MessageIcon": "question",
                        "MessageContent": "Coughing or wheezing",
                        "ReturnFieldType": "Range",
                        "ReturnDataRangeLow": "0",
                        "ReturnDataRangeHigh": "9",
                        "ReturnValidAnswers": null,
                        "PatientAnswer": null,
                        "ResponseDate": null
                    },
                    {
                        "MessageID": "CF_SYM_13",
                        "Obs_Key": "Symptom",
                        "ParentID": "603",
                        "MessageIcon": "question",
                        "MessageContent": "Chest pain or Chest tightness",
                        "ReturnFieldType": "Range",
                        "ReturnDataRangeLow": "0",
                        "ReturnDataRangeHigh": "9",
                        "ReturnValidAnswers": null,
                        "PatientAnswer": null,
                        "ResponseDate": null
                    },
                    {
                        "MessageID": "CF_SYM_14",
                        "Obs_Key": "Symptom",
                        "ParentID": "603",
                        "MessageIcon": "question",
                        "MessageContent": "Fatigue",
                        "ReturnFieldType": "Range",
                        "ReturnDataRangeLow": "0",
                        "ReturnDataRangeHigh": "9",
                        "ReturnValidAnswers": null,
                        "PatientAnswer": null,
                        "ResponseDate": null
                    },
                    {
                        "MessageID": "CF_SYM_15",
                        "Obs_Key": "Symptom",
                        "ParentID": "603",
                        "MessageIcon": "question",
                        "MessageContent": "Weakness or dizziness",
                        "ReturnFieldType": "Range",
                        "ReturnDataRangeLow": "0",
                        "ReturnDataRangeHigh": "9",
                        "ReturnValidAnswers": null,
                        "PatientAnswer": null,
                        "ResponseDate": null
                    },
                    {
                        "MessageID": "CF_SYM_16",
                        "Obs_Key": "Symptom",
                        "ParentID": "603",
                        "MessageIcon": "question",
                        "MessageContent": "Swelling in legs/feet",
                        "ReturnFieldType": "Range",
                        "ReturnDataRangeLow": "0",
                        "ReturnDataRangeHigh": "9",
                        "ReturnValidAnswers": null,
                        "PatientAnswer": null,
                        "ResponseDate": null
                    },
                    {
                        "MessageID": "CF_SYM_17",
                        "Obs_Key": "Symptom",
                        "ParentID": "603",
                        "MessageIcon": "question",
                        "MessageContent": "Feeling down, a sense of helplessness or sleep changes/problems",
                        "ReturnFieldType": "Range",
                        "ReturnDataRangeLow": "0",
                        "ReturnDataRangeHigh": "9",
                        "ReturnValidAnswers": null,
                        "PatientAnswer": null,
                        "ResponseDate": null
                    },
                    {
                        "MessageID": "CF_SYM_70",
                        "Obs_Key": "Call",
                        "ParentID": "603",
                        "MessageIcon": "question",
                        "MessageContent": "Please have clinic call me",
                        "ReturnFieldType": "Range",
                        "ReturnDataRangeLow": "0",
                        "ReturnDataRangeHigh": "9",
                        "ReturnValidAnswers": null,
                        "PatientAnswer": null,
                        "ResponseDate": null
                    }
                ]
            }

       }
    ]
}
